Metadata-Version: 2.1
Name: unstdio
Version: 0.0.4
Summary: unstdio for inplace manipulation of stdio
Home-page: https://github.com/eaybek/unstdio
Author: Erdem Aybek
Author-email: eaybek@gmail.com
License: UNKNOWN
Platform: UNKNOWN
Classifier: Programming Language :: Python :: 3
Classifier: License :: OSI Approved :: MIT License
Classifier: Operating System :: POSIX :: Linux
Classifier: Development Status :: 1 - Planning
Requires-Python: >=3.6
